automatic_goggles-0.6.0.dist-info/licenses/LICENSE
transtype/__init__.py
transtype/models.py
transtype/processor.py
automatic_goggles-0.6.0.dist-info/METADATA
automatic_goggles-0.6.0.dist-info/WHEEL
automatic_goggles-0.6.0.dist-info/top_level.txt
automatic_goggles-0.6.0.dist-info/RECORD
