Metadata-Version: 2.4
Name: automatic-goggles
Version: 0.6.0
Summary: A package for extracting structured fields from call transcripts and evaluating conversation quality with confidence scores
Home-page: https://github.com/ashishorkalra/automatic-goggles
Author: Ashish Kalra
Author-email: Your Name <your.email@example.com>
License: MIT
Project-URL: Homepage, https://github.com/ashishorkalra/automatic-goggles-public
Project-URL: Repository, https://github.com/ashishorkalra/automatic-goggles-public
Project-URL: Documentation, https://github.com/ashishorkalra/automatic-goggles-public#readme
Project-URL: Bug Reports, https://github.com/ashishorkalra/automatic-goggles-public/issues
Keywords: transcript,processing,field extraction,AI,natural language processing
Classifier: Programming Language :: Python :: 3
Classifier: Programming Language :: Python :: 3.9
Classifier: Programming Language :: Python :: 3.10
Classifier: Programming Language :: Python :: 3.11
Classifier: Programming Language :: Python :: 3.12
Classifier: License :: OSI Approved :: MIT License
Classifier: Operating System :: OS Independent
Classifier: Development Status :: 3 - Alpha
Classifier: Intended Audience :: Developers
Classifier: Topic :: Software Development :: Libraries :: Python Modules
Classifier: Topic :: Scientific/Engineering :: Artificial Intelligence
Requires-Python: >=3.9,<3.13
License-File: LICENSE
Requires-Dist: dspy==2.6.8
Requires-Dist: openai>=1.0.0
Requires-Dist: pydantic>=2.0.0
Provides-Extra: dev
Requires-Dist: pytest>=7.0.0; extra == "dev"
Requires-Dist: pytest-cov>=4.0.0; extra == "dev"
Dynamic: author
Dynamic: home-page
Dynamic: license-file
Dynamic: requires-python
